{
    "lastUpdated": "18-07-2026 | 12:13 PM IST",
    "maharashtra": [
        {
            "id": "7f973d814bbb",
            "feed": "lokmat",
            "title": "“नागपूरच्या कार्यक्रमावरुन लक्ष भरकटवण्यासाठीच वांगचुक यांच्यावर दडपशाही”; राऊतांचा आरोप",
            "source": {
                "id": "lokmat",
                "name": "Lokmat",
                "website": "https://www.lokmat.com",
                "category": "maharashtra"
            },
            "published": "2026-07-18T12:08:33",
            "url": "https://www.lokmat.com/nagpur/oppression-against-wangchuk-to-divert-attention-from-nagpur-program-says-sanjay-raut-a-a597/",
            "image": "https://d3pc1xvrcw35tl.cloudfront.net/images/686x514/raut-ram-mandir-sonam_2026071744836.jpeg",
            "isBreaking": false,
            "category_reason": "feed"
        },
        {
            "id": "d5898b897c66",
            "feed": "lokmat",
            "title": "Shravani Kudale: विषय काेणताही असाे ‘इन डेप्थ’ अभ्यास केला पाहिजे; 'नीट' मध्ये अव्वल ठरलेल्या श्रावणीचे मत",
            "source": {
                "id": "lokmat",
                "name": "Lokmat",
                "website": "https://www.lokmat.com",
                "category": "maharashtra"
            },
            "published": "2026-07-18T12:07:44",
            "url": "https://www.lokmat.com/pune/no-matter-what-the-subject-one-should-study-it-in-depth-says-shravani-kudale-who-topped-in-neet-a-a727/",
            "image": "https://d3pc1xvrcw35tl.cloudfront.net/images/686x514/nm-student-4-a_2026071744837.jpg",
            "isBreaking": false,
            "category_reason": "feed"
        },
        {
            "id": "ff4e5ed86c14",
            "feed": "lokmat",
            "title": "Kolhapur-Gokul Dudh Sangh Election: 'गोकुळ'ने सभासद रद्दच्या नोटीसा बजावलेल्या संस्था एकवटल्या",
            "source": {
                "id": "lokmat",
                "name": "Lokmat",
                "website": "https://www.lokmat.com",
                "category": "maharashtra"
            },
            "published": "2026-07-18T12:04:06",
            "url": "https://www.lokmat.com/kolhapur/organizations-that-had-issued-notices-to-cancel-members-by-gokul-dudh-sangh-unite-a-a746/",
            "image": "https://d3pc1xvrcw35tl.cloudfront.net/images/686x514/gokul-news-court-sanstha-today-news_2026071744833.jpg",
            "isBreaking": false,
            "category_reason": "feed"
        },
        {
            "id": "3e978b64a687",
            "feed": "loksatta",
            "title": "देशात दडपशाही, भाजपच्या पायाखालची वाळू सरकली, संजय राऊत यांचा हल्लाबोल",
            "source": {
                "id": "loksatta",
                "name": "Loksatta",
                "website": "https://www.loksatta.com",
                "category": "maharashtra"
            },
            "published": "2026-07-18T12:02:05",
            "url": "https://www.loksatta.com/nagpur/sanjay-raut-nagpur-ramraksha-pathan-sonam-wangchuk-bjp-target-uddhav-thackeray-sap-05-6026599/",
            "image": "https://images.loksattaimg.com/2026/07/New-Project-2026-07-18T115325.982.jpg",
            "isBreaking": false,
            "category_reason": "feed"
        },
        {
            "id": "b0d6f1a0c09d",
            "feed": "lokmat",
            "title": "अखेर प्रतीक्षा संपणार! म्हाडाच्या मुंबईतील २,६४० घरांची लॉटरी पुढच्या आठवड्यात",
            "source": {
                "id": "lokmat",
                "name": "Lokmat",
                "website": "https://www.lokmat.com",
                "category": "maharashtra"
            },
            "published": "2026-07-18T12:01:30",
            "url": "https://www.lokmat.com/mumbai/the-wait-is-finally-over-mhadas-lottery-for-2640-houses-in-mumbai-next-week-a-a629/",
            "image": "https://d3pc1xvrcw35tl.cloudfront.net/images/686x514/mhada-new-1108dssf_2026061725979.jpg",
            "isBreaking": false,
            "category_reason": "feed"
        }
    ],
    "india": [
        {
            "id": "904d35820dac",
            "feed": "maharashtratimes",
            "title": "Atul Pawar : अतुल साप चावल्याने गेला! स्कूल संचालकाच्या बायकोचे स्कूल बसचालकाशी संबंध, पतीचा काटा काढला, पण पवार कुटुंबाने छडा लावलाच",
            "source": {
                "id": "maharashtratimes",
                "name": "Maharashtra Times",
                "website": "https://maharashtratimes.com",
                "category": null
            },
            "published": "2026-07-18T12:09:05",
            "url": "https://maharashtratimes.com/india-news/meerut-school-director-atul-pawar-murder-wife-damini-kills-with-school-bus-driver-tushar-snake-byte/articleshow/132475148.cms",
            "image": "",
            "isBreaking": false,
            "category_reason": "url"
        },
        {
            "id": "8bbc629c584a",
            "feed": "loksatta",
            "title": "जिकडे तिकडे प्रचंड पैसा दिसणार; मंगळाचे नक्षत्र गोचर ‘या’ तीन राशींना हवं ते मिळवून देणार, रातोरात आयुष्य बदलणार",
            "source": {
                "id": "loksatta",
                "name": "Loksatta",
                "website": "https://www.loksatta.com",
                "category": null
            },
            "published": "2026-07-18T12:06:18",
            "url": "https://www.loksatta.com/astrology/mangal-nakshatra-gochar-2026-mithun-kanya-and-makar-zodic-sign-will-get-high-career-growth-and-healthy-lifestyle-sap-20-6026489/",
            "image": "https://images.loksattaimg.com/2026/07/New-Project-2026-07-18T120328.732.jpg",
            "isBreaking": false,
            "category_reason": "default"
        },
        {
            "id": "a38fd155913c",
            "feed": "esakal",
            "title": "सोनम वांगचुकना हटवण्यासाठी ३० सेकंदाचा प्लॅन, पहाटे ३ पासून हालचाली; साध्या वेशात पोलीस, चादरीचा पडदा लावून उचललं",
            "source": {
                "id": "esakal",
                "name": "eSakal",
                "website": "https://www.esakal.com",
                "category": null
            },
            "published": "2026-07-18T12:04:49",
            "url": "https://www.esakal.com/desh/sonam-wangchuk-hospital-shift-delhi-police-executed-30-second-operation-at-jantar-mantar-details-surface-ssy93",
            "image": "https://cf-images.assettype.com/esakal/2026-07-18/yjg3golg/sonam-wangchuk-jantar-mantar.jpg",
            "isBreaking": false,
            "category_reason": "url"
        },
        {
            "id": "cf395db1549b",
            "feed": "maharashtratimes",
            "title": "Ek Hota Malin Trailer : 'एक होतं माळीण' एका पावसात होत्याचं नव्हतं झालं, नैसर्गिक आपत्तीवर आधारित पहिला मराठी चित्रपट, ट्रेलरने वेधले लक्ष",
            "source": {
                "id": "maharashtratimes",
                "name": "Maharashtra Times",
                "website": "https://maharashtratimes.com",
                "category": null
            },
            "published": "2026-07-18T12:03:40",
            "url": "https://maharashtratimes.com/entertainment/entertainment-news/bollywood-news/ek-hota-malin-new-marathi-movie-trailer-based-on-natural-disaster/articleshow/132474819.cms",
            "image": "",
            "isBreaking": false,
            "category_reason": "url"
        },
        {
            "id": "a6918b40275c",
            "feed": "esakal",
            "title": "Premium|Jhabua Dolls : भिल्ल जीवनाचा आरसा झाबुआ बाहुल्या",
            "source": {
                "id": "esakal",
                "name": "eSakal",
                "website": "https://www.esakal.com",
                "category": null
            },
            "published": "2026-07-18T12:00:00",
            "url": "https://www.esakal.com/premium-article/saptahik/jhabua-cloth-dolls-tribal-handicraft-eco-friendly-dolls-madhya-pradesh-traditional-art-recycled-fabric-indian-folk-craft-amp17",
            "image": "https://cf-images.assettype.com/esakal/2026-07-13/nc3vh4kn/Abhi-17.jpg",
            "isBreaking": false,
            "category_reason": "keyword"
        }
    ],
    "world": [
        {
            "id": "bd31d62590e8",
            "feed": "esakal",
            "title": "US Visa: महिनाभरात नोकरी मिळवा, अन्यथा अमेरिका सोडा! व्हिसा नियमांतील बदलांमुळे विद्यार्थी अडचणीत",
            "source": {
                "id": "esakal",
                "name": "eSakal",
                "website": "https://www.esakal.com",
                "category": null
            },
            "published": "2026-07-18T11:55:29",
            "url": "https://www.esakal.com/global/us-visa-new-rules-students-job-within-one-month-or-leave-america-impact-on-indian-students-marathi-vsd00",
            "image": "https://cf-images.assettype.com/esakal/2026-07-18/sn1s47ca/Copy-of-Copy-of-banner-2026-07-18T114438.377.jpg",
            "isBreaking": false,
            "category_reason": "url"
        },
        {
            "id": "e61c8e77ba41",
            "feed": "lokmat",
            "title": "विद्यार्थी, पत्रकारांना अमेरिकेचे व्हिसा नियम कडक; अमेरिकेतील भारतीयांना फटका बसण्याची शक्यता",
            "source": {
                "id": "lokmat",
                "name": "Lokmat",
                "website": "https://www.lokmat.com",
                "category": "world"
            },
            "published": "2026-07-18T10:08:01",
            "url": "https://www.lokmat.com/international/us-visa-rules-tightened-for-students-journalists-indians-in-america-likely-to-be-affected-a-a629/",
            "image": "https://d3pc1xvrcw35tl.cloudfront.net/images/686x514/zvsdc768d_2023051022254.jpg",
            "isBreaking": false,
            "category_reason": "feed"
        },
        {
            "id": "afff3c70b98e",
            "feed": "lokmat",
            "title": "इराणवर भीषण प्रहार! वीज यंत्रणा, बंदरे, पूल उद्ध्वस्त; कतार-कुवेतवर इराणचा क्षेपणास्त्र मारा",
            "source": {
                "id": "lokmat",
                "name": "Lokmat",
                "website": "https://www.lokmat.com",
                "category": "world"
            },
            "published": "2026-07-18T09:58:02",
            "url": "https://www.lokmat.com/international/terrible-attack-on-iran-power-system-ports-bridges-destroyed-iranian-missile-hits-qatar-kuwait-a-a629/",
            "image": "https://d3pc1xvrcw35tl.cloudfront.net/images/686x514/us-iran-war-nsuce83_2026071744776.jpg",
            "isBreaking": false,
            "category_reason": "feed"
        },
        {
            "id": "7c3dc6b0c619",
            "feed": "loksatta",
            "title": "ऑलिम्पिक आख्यान: ऑलिम्पिक मैदानावर बहिष्कारास्त्र!",
            "source": {
                "id": "loksatta",
                "name": "Loksatta",
                "website": "https://www.loksatta.com",
                "category": null
            },
            "published": "2026-07-18T04:53:06",
            "url": "https://www.loksatta.com/sampadkiya/columns/olympic-history-boycott-politics-cold-war-usa-ussr-analysis-amy-95-6026156/",
            "image": "https://images.loksattaimg.com/2026/07/Olympic-History-Boycott-Politics.jpg",
            "isBreaking": false,
            "category_reason": "keyword"
        },
        {
            "id": "affc525a8a29",
            "feed": "loksatta",
            "title": "गर्भपाताविषयी मौन का?",
            "source": {
                "id": "loksatta",
                "name": "Loksatta",
                "website": "https://www.loksatta.com",
                "category": null
            },
            "published": "2026-07-18T01:07:00",
            "url": "https://www.loksatta.com/chaturang/women-miscarriage-at-workplace-quest-global-survey-maternity-benefit-law-zws-70-6025012/",
            "image": "https://images.loksattaimg.com/2026/07/chatu02-8.jpg",
            "isBreaking": false,
            "category_reason": "keyword"
        }
    ],
    "sports": [
        {
            "id": "f83544ab3d35",
            "feed": "esakal",
            "title": "Messi vs Maradona: मेस्सी अजूनही मॅराडोनापेक्षा मोठा नाही? भारतीय फुटबॉल दिग्गजाचं धक्कादायक मत",
            "source": {
                "id": "esakal",
                "name": "eSakal",
                "website": "https://www.esakal.com",
                "category": null
            },
            "published": "2026-07-18T12:12:12",
            "url": "https://www.esakal.com/krida/messi-vs-maradona-baichung-bhutia-big-statement-before-fifa-world-cup-final-argentina-vs-spain-vsb99",
            "image": "https://cf-images.assettype.com/esakal/2026-07-18/174tkr8r/fifa-2026-4.jpg",
            "isBreaking": false,
            "category_reason": "url"
        },
        {
            "id": "ce4043d74368",
            "feed": "maharashtratimes",
            "title": "FIFA World Cup 2026 : फिफा फुटबॉल फायनलमध्ये तिसऱ्या नंबरसाठी आज इंग्लंड-फ्रान्समध्ये लढत, 279 कोटी कोटीचं बक्षीस कोण जिंकणार?",
            "source": {
                "id": "maharashtratimes",
                "name": "Maharashtra Times",
                "website": "https://maharashtratimes.com",
                "category": "sports"
            },
            "published": "2026-07-18T12:09:54",
            "url": "https://maharashtratimes.com/sports/football/news/fifa-world-cup-2026-third-place-playoff-france-vs-england-kylian-mbappe-chance-for-golden-boot/articleshow/132474706.cms",
            "image": "",
            "isBreaking": false,
            "category_reason": "feed"
        },
        {
            "id": "eddef23bb1a0",
            "feed": "loksatta",
            "title": "IND vs ENG: लॉर्ड्सच्या ऐतिहासिक मैदानावर ‘आर-पारची’ लढाई!कसा आहे दोन्ही संघांचा हेड टू हेड रेकॉर्ड?",
            "source": {
                "id": "loksatta",
                "name": "Loksatta",
                "website": "https://www.loksatta.com",
                "category": null
            },
            "published": "2026-07-18T11:58:52",
            "url": "https://www.loksatta.com/krida/india-vs-england-head-to-head-record-at-lords-cricket-ground-cricket-news-in-marathi-rohit-sharma-retirement-amd-2000-6026636/",
            "image": "https://images.loksattaimg.com/2026/07/IND-vs-ENG-29.jpg",
            "isBreaking": false,
            "category_reason": "url"
        }
    ],
    "business": [
        {
            "id": "79a98c557130",
            "feed": "lokmat",
            "title": "Jalna Nanded Expressway : विकास की विनाश? वडिलोपार्जित फळबागेवर चालणार कुऱ्हाड, शेतकऱ्यांचे डोळे पाणावले",
            "source": {
                "id": "lokmat",
                "name": "Lokmat",
                "website": "https://www.lokmat.com",
                "category": null
            },
            "published": "2026-07-18T12:08:33",
            "url": "https://www.lokmat.com/agriculture/farming-ideas/latest-news-jalna-nanded-expressway-development-or-destruction-the-axe-will-be-used-on-ancestral-orchards-farmers-eyes-watered-a-a1003/",
            "image": "https://d3pc1xvrcw35tl.cloudfront.net/images/686x514/jalna-nanded-expressway-1_2026071744834.jpg",
            "isBreaking": false,
            "category_reason": "url"
        },
        {
            "id": "74bbc888e0c2",
            "feed": "maharashtratimes",
            "title": "रिलायन्स ब्रॉडकास्टनं केली 'ONE BIG WORLD' ची घोषणा, AI-सक्षम भविष्यासाठी मीडिया आणि मनोरंजन क्षेत्रातील नवा अध्याय",
            "source": {
                "id": "maharashtratimes",
                "name": "Maharashtra Times",
                "website": "https://maharashtratimes.com",
                "category": "business"
            },
            "published": "2026-07-18T11:35:38",
            "url": "https://maharashtratimes.com/business/business-news/rbnl-launches-one-big-world-to-transform-sp-indias-media-and-entertainment-landscape/articleshow/132474602.cms",
            "image": "",
            "isBreaking": false,
            "category_reason": "feed"
        },
        {
            "id": "7fc959a1ad33",
            "feed": "loksatta",
            "title": "“ती हसत नाही तेव्हा…”, प्रियांका चोप्रा साऊथ इंडस्ट्री गाजवणार! एस एस राजामौलींनी शेअर केले फोटो, म्हणाले…",
            "source": {
                "id": "loksatta",
                "name": "Loksatta",
                "website": "https://www.loksatta.com",
                "category": null
            },
            "published": "2026-07-18T11:19:33",
            "url": "https://www.loksatta.com/manoranjan/bollywood/priyanka-chopra-varanasi-movie-first-look-mandakini-ss-rajamouli-mahesh-babu-actress-birthday-nsp-98-6026516/",
            "image": "https://images.loksattaimg.com/2026/07/pri-1.jpg",
            "isBreaking": false,
            "category_reason": "keyword"
        }
    ]
}